{
  "name": "sprag-indexer-fallback",
  "dataSourceName": "sprag-datasource",
  "targetIndexName": "sprag-index",
  "skillsetName": "sprag-skillset-fallback",
  "schedule": { "interval": "PT24H" },
  "parameters": {
    "maxFailedItems": -1,
    "maxFailedItemsPerBatch": -1,
    "batchSize": 10,
    "configuration": {
      "dataToExtract": "contentAndMetadata",
      "parsingMode": "default",
      "imageAction": "none",
      "indexedFileNameExtensions": ".doc,.csv"
    }
  },
  "fieldMappings": [
    {
      "sourceFieldName": "metadata_storage_path",
      "targetFieldName": "chunk_id",
      "mappingFunction": {"name": "fixedLengthEncode"}
    }
  ],
  "outputFieldMappings": []
}
